{
  "type": [
    "BuyersGuide"
  ],
  "properties": {
    "copyrightYear": [
      2013
    ],
    "copyrightHolder": [
      {
        "type": [
          "LaborUnion"
        ],
        "properties": {
          "name": [
            "UNITE HERE"
          ]
        }
      }
    ],
    "judgment": [
      {
        "type": [
          "Judgment"
        ],
        "properties": {
          "judgmentType": [
            "Good"
          ],
          "name": [
            "Please Patronize"
          ],
          "target": [
            {
              "type": [
                "Hotel"
              ],
              "properties": {
                "name": [
                  "5 Calgary Downtown Suites"
                ],
                "address": [
                  {
                    "type": [
                      "PostalAddress"
                    ],
                    "properties": {
                      "locality": [
                        "Calgary"
                      ],
                      "region": [
                        "AB"
                      ],
                      "telephone": [
                        "(403) 263-0520"
                      ],
                      "addressCountry": [
                        "CA"
                      ],
                      "streetAddress": [
                        "618 -5Th Ave. SW"
                      ],
                      "postalCode": [
                        "T2P 0M7"
                      ]
                    }
                  }
                ]
              }
            }
          ]
        }
      },
    ],
    "name": [
      "Union Hotel Guide"
    ],
    "author": [
      {
        "type": [
          "LaborUnion"
        ],
        "properties": {
          "name": [
            "UNITE HERE"
          ]
        }
      }
    ]
  }
}
